[
    {
        "id": 1,
        "image_url": "https://example.com/images/image1.jpg"
    },
    {
        "id": 2,
        "image_url": "https://example.com/images/image2.jpg"
    },
    {
        "id": 3,
        "image_url": "https://example.com/images/image3.jpg"
    },
    {
        "id": 4,
        "image_url": "https://example.com/images/image4.jpg"
    },
    {
        "id": 5,
        "image_url": "https://example.com/images/image5.jpg"
    },
    {
        "id": 6,
        "image_url": "https://example.com/images/image6.jpg"
    },
    {
        "id": 7,
        "image_url": "https://example.com/images/image7.jpg"
    },
    {
        "id": 8,
        "image_url": "https://example.com/images/image8.jpg"
    },
    {
        "id": 9,
        "image_url": "https://example.com/images/image9.jpg"
    },
    {
        "id": 10,
        "image_url": "https://example.com/images/image10.jpg"
    }
]
